puantum-999.999.999.dist-info/METADATA
puantum-999.999.999.dist-info/WHEEL
puantum-999.999.999.dist-info/licenses/license.md
puantum/__init__.py
puantum/__init__.pyi
puantum/__internal__.cp313-win_amd64.pyd
puantum/classic/__init__.py
puantum/classic/__init__.pyi
puantum/quantum/__init__.py
puantum/quantum/__init__.pyi
puantum/quantum/dsa/__init__.py
puantum/quantum/dsa/__init__.pyi
puantum/quantum/dsa/__internal__.py
puantum/quantum/dsa/__internal__.pyi
puantum/quantum/kem/__init__.py
puantum/quantum/kem/__init__.pyi
puantum/quantum/kem/__internal__.py
puantum/quantum/kem/__internal__.pyi
puantum-999.999.999.dist-info/RECORD
