Metadata-Version: 2.4
Name: puantum
Version: 999.999.999
Classifier: Programming Language :: Python :: 3
Classifier: Programming Language :: Rust
Classifier: Operating System :: OS Independent
Classifier: License :: Public Domain
Classifier: License :: OSI Approved :: The Unlicense (Unlicense)
License-File: license.md
Summary: Python Cryptography
Keywords: python,cryptography,quantum,security
Author-email: Anonymous <217687495+1xfakebit@users.noreply.github.com>
License: Unlicense
Project-URL: source, https://github.com/1xfakebit/puantum
Project-URL: x, https://x.com/1xfakebit
